[
    {
        "product_id_i": 590249,
        "type_i": 1,
        "lang_code_s": "en",
        "name": "File",
        "sku": "0b071706807f1b3b",
        "GroupFamilyName_s": "13325-0b071706807f1b3b",
        "modification_timestamp_tdt": "2020-05-31T20:05:43Z",
        "modification_timestamp_s": "2020-05-31 20:05:43",
        "group_id_i": 13325,
        "product_code_t": "0b071706807f1b3b",
        "FamilyName_t": "0b071706807f1b3b",
        "objHier_objectType_t": "FILE",
        "objHier_isFictiveItem_t": "false",
        "objHier_isDeleted_t": "false",
        "objDesc_objectName_t": "בועיינה, בועינה - נוג'ידאת",
        "objDesc_objectName_tphon": "בועיינה, בועינה - נוג'ידאת",
        "objDesc_objectName_e_t": "בועיינה, בועינה - נוג'ידאת",
        "objDesc_objectDesc_t": "בקשה לשינוי שם המועצה המקומית והנמקה",
        "objDesc_objectDesc_tar": "בקשה לשינוי שם המועצה המקומית והנמקה",
        "objDesc_objectDesc_tfr": "בקשה לשינוי שם המועצה המקומית והנמקה",
        "objDesc_objectDesc_e_t": "בקשה לשינוי שם המועצה המקומית והנמקה",
        "objAttr_isGsaFeedEnabled_t": "true",
        "objDate_datingPeriodStart_t": "01/07/1987",
        "objDate_datingPeriodStartYear_t": "1987",
        "objDate_datingPeriodEnd_t": "31/08/1990",
        "objDate_datingPeriodEndYear_t": "1990",
        "objHier_archiveId_t": "0b07170680020246",
        "objHier_archiveName_t": "ועדת השמות הממשלתית",
        "objHier_archiveName_e_t": "ועדת השמות הממשלתית",
        "objHier_parentObjectId_t": "0b07170680359f2d",
        "objAttr_archiveEditDate_t": "2020-05-24",
        "objAttr_materialType_t": "תיק מסמכים",
        "objAttr_mediaType_t": "מסמך",
        "objAttr_mediaTypeOrig_t": "תיק מסמכים",
        "addAttr_objectName_t": "ועדת השמות הממשלתית",
        "addAttr_orgTree_t": "משרד ראש הממשלה/מזכירות הממשלה/ועדת השמות הממשלתית",
        "addAttr_orgTree_e_t": "משרד ראש הממשלה/מזכירות הממשלה/ועדת השמות הממשלתית",
        "addAttr_type_t": "תיק מסמכים",
        "objHier_objectReference_t": "ISA-PMO-GovNamesCommittee-000d7bf",
        "addAttr_statusChasifa_t": "חסוי",
        "addAttr_tikOldNumber_t": "ג - 15 / 12407",
        "addAttr_tikOldNumber_e_t": "ג - 15 / 12407",
        "addAttr_matsa_t": "עבר דיגיטציה",
        "addAttr_taarichMiuiadHashifa_t": "2005",
        "addAttr_mezaheh_t": "ISA-PMO-GovNamesCommittee-000d7bf",
        "addAttr_mezaheh_e_t": "ISA-PMO-GovNamesCommittee-000d7bf",
        "addAttr_rimonObjectName_t": "בועיינה, בועינה - נוג'ידאת",
        "objDate_datingPeriodStartMonth_t": "07",
        "objDate_datingPeriodEndMonth_t": "08",
        "task_t": "1597",
        "altRef_relationType_t": "סימול מקורי",
        "contentEntity_t": "0b07170680020246",
        "product_code_s": "0b071706807f1b3b",
        "FamilyName_s": "0b071706807f1b3b",
        "objHier_objectType_s": "FILE",
        "objHier_isFictiveItem_s": "false",
        "objHier_isDeleted_s": "false",
        "objDesc_objectName_s": "בועיינה, בועינה - נוג'ידאת",
        "objDesc_objectDesc_s": "בקשה לשינוי שם המועצה המקומית והנמקה",
        "objAttr_isGsaFeedEnabled_s": "true",
        "objDate_datingPeriodStart_s": "01/07/1987",
        "objDate_datingPeriodStartYear_s": "1987",
        "objDate_datingPeriodEnd_s": "31/08/1990",
        "objDate_datingPeriodEndYear_s": "1990",
        "objHier_archiveId_s": "0b07170680020246",
        "objHier_archiveName_s": "ועדת השמות הממשלתית",
        "objHier_parentObjectId_s": "0b07170680359f2d",
        "objAttr_archiveEditDate_s": "2020-05-24",
        "objAttr_materialType_s": "תיק מסמכים",
        "objAttr_mediaType_s": "מסמך",
        "objAttr_mediaTypeOrig_s": "תיק מסמכים",
        "addAttr_objectName_s": "ועדת השמות הממשלתית",
        "addAttr_orgTree_s": "משרד ראש הממשלה/מזכירות הממשלה/ועדת השמות הממשלתית",
        "addAttr_type_s": "תיק מסמכים",
        "objHier_objectReference_s": "ISA-PMO-GovNamesCommittee-000d7bf",
        "addAttr_statusChasifa_s": "חסוי",
        "addAttr_tikOldNumber_s": "ג - 15 / 12407",
        "addAttr_matsa_s": "עבר דיגיטציה",
        "addAttr_taarichMiuiadHashifa_s": "2005",
        "addAttr_mezaheh_s": "ISA-PMO-GovNamesCommittee-000d7bf",
        "addAttr_rimonObjectName_s": "בועיינה, בועינה - נוג'ידאת",
        "objDate_datingPeriodStartMonth_s": "07",
        "objDate_datingPeriodEndMonth_s": "08",
        "task_s": "1597",
        "altRef_relationType_s": "סימול מקורי",
        "contentEntity_s": "0b07170680020246",
        "product_code_ss": [
            "0b071706807f1b3b"
        ],
        "FamilyName_ss": [
            "0b071706807f1b3b"
        ],
        "objHier_objectType_ss": [
            "FILE"
        ],
        "objHier_isFictiveItem_ss": [
            "false"
        ],
        "objHier_isDeleted_ss": [
            "false"
        ],
        "objDesc_objectName_ss": [
            "בועיינה, בועינה - נוג'ידאת"
        ],
        "objDesc_objectDesc_ss": [
            "בקשה לשינוי שם המועצה המקומית והנמקה"
        ],
        "objAttr_isGsaFeedEnabled_ss": [
            "true"
        ],
        "objDate_datingPeriodStart_ss": [
            "01/07/1987"
        ],
        "objDate_datingPeriodStartYear_ss": [
            "1987"
        ],
        "objDate_datingPeriodEnd_ss": [
            "31/08/1990"
        ],
        "objDate_datingPeriodEndYear_ss": [
            "1990"
        ],
        "objHier_archiveId_ss": [
            "0b07170680020246"
        ],
        "objHier_archiveName_ss": [
            "ועדת השמות הממשלתית"
        ],
        "objHier_parentObjectId_ss": [
            "0b07170680359f2d"
        ],
        "objAttr_archiveEditDate_ss": [
            "2020-05-24"
        ],
        "objAttr_materialType_ss": [
            "תיק מסמכים"
        ],
        "objAttr_mediaType_ss": [
            "מסמך"
        ],
        "objAttr_mediaTypeOrig_ss": [
            "תיק מסמכים"
        ],
        "addAttr_objectName_ss": [
            "ועדת השמות הממשלתית"
        ],
        "addAttr_orgTree_ss": [
            "משרד ראש הממשלה/מזכירות הממשלה/ועדת השמות הממשלתית"
        ],
        "addAttr_type_ss": [
            "תיק מסמכים"
        ],
        "objHier_objectReference_ss": [
            "ISA-PMO-GovNamesCommittee-000d7bf"
        ],
        "addAttr_statusChasifa_ss": [
            "חסוי"
        ],
        "addAttr_tikOldNumber_ss": [
            "ג - 15 / 12407"
        ],
        "addAttr_matsa_ss": [
            "עבר דיגיטציה"
        ],
        "addAttr_taarichMiuiadHashifa_ss": [
            "2005"
        ],
        "addAttr_mezaheh_ss": [
            "ISA-PMO-GovNamesCommittee-000d7bf"
        ],
        "addAttr_rimonObjectName_ss": [
            "בועיינה, בועינה - נוג'ידאת"
        ],
        "objDate_datingPeriodStartMonth_ss": [
            "07"
        ],
        "objDate_datingPeriodEndMonth_ss": [
            "08"
        ],
        "task_ss": [
            "1597"
        ],
        "altRef_relationType_ss": [
            "סימול מקורי"
        ],
        "contentEntity_ss": [
            "0b07170680020246"
        ],
        "solr_index_timestamp_tdt": "2021-05-11T10:57:27Z",
        "solr_index_timestamp_s": "2021-05-11 10:57:27",
        "file_has_items_s": "",
        "organizations_s": "ועדת השמות הממשלתית",
        "organizations_t": "ועדת השמות הממשלתית",
        "organizations_ss": [
            "ועדת השמות הממשלתית"
        ],
        "enrichment_s": "",
        "enrichment_t": "",
        "enrichment_e_t": "",
        "enrichment_1_s": "",
        "enrichment_1_t": "",
        "enrichment_2_s": "",
        "enrichment_2_t": "",
        "event_s": "",
        "event_t": "",
        "subject_s": "",
        "subject_t": "",
        "place_s": "",
        "place_t": "",
        "person_s": "",
        "person_t": "",
        "person_tphon": "",
        "project_s": "",
        "project_t": "",
        "attachment_content_t": "",
        "attachment_content_tar": "",
        "attachment_content_tfr": "",
        "attachment_content_e_t": "",
        "group_id_is": [
            1
        ],
        "objectDatingYear_ss": [
            "1987",
            "1990"
        ],
        "objDesc_objectDesc_short_s": "בקשה לשינוי שם המועצה המקומית והנמקה",
        "sig_media_type_s": "תיק",
        "sig_media_type_ss": [
            "תיק"
        ],
        "attachment_url_s": "n",
        "objHier_attachment_attachmentType_s": "n",
        "objectDatingMonths_ss": [
            "07/1987",
            "08/1987",
            "09/1987",
            "10/1987",
            "11/1987",
            "12/1987",
            "01/1988",
            "02/1988",
            "03/1988",
            "04/1988",
            "05/1988",
            "06/1988",
            "07/1988",
            "08/1988",
            "09/1988",
            "10/1988",
            "11/1988",
            "12/1988",
            "01/1989",
            "02/1989",
            "03/1989",
            "04/1989",
            "05/1989",
            "06/1989",
            "07/1989",
            "08/1989",
            "09/1989",
            "10/1989",
            "11/1989",
            "12/1989",
            "01/1990",
            "02/1990",
            "03/1990",
            "04/1990",
            "05/1990",
            "06/1990",
            "07/1990",
            "08/1990"
        ],
        "objectDatingMonths_dts": [
            "1987-07-01T00:00:00Z",
            "1987-08-01T00:00:00Z",
            "1987-09-01T00:00:00Z",
            "1987-10-01T00:00:00Z",
            "1987-11-01T00:00:00Z",
            "1987-12-01T00:00:00Z",
            "1988-01-01T00:00:00Z",
            "1988-02-01T00:00:00Z",
            "1988-03-01T00:00:00Z",
            "1988-04-01T00:00:00Z",
            "1988-05-01T00:00:00Z",
            "1988-06-01T00:00:00Z",
            "1988-07-01T00:00:00Z",
            "1988-08-01T00:00:00Z",
            "1988-09-01T00:00:00Z",
            "1988-10-01T00:00:00Z",
            "1988-11-01T00:00:00Z",
            "1988-12-01T00:00:00Z",
            "1989-01-01T00:00:00Z",
            "1989-02-01T00:00:00Z",
            "1989-03-01T00:00:00Z",
            "1989-04-01T00:00:00Z",
            "1989-05-01T00:00:00Z",
            "1989-06-01T00:00:00Z",
            "1989-07-01T00:00:00Z",
            "1989-08-01T00:00:00Z",
            "1989-09-01T00:00:00Z",
            "1989-10-01T00:00:00Z",
            "1989-11-01T00:00:00Z",
            "1989-12-01T00:00:00Z",
            "1990-01-01T00:00:00Z",
            "1990-02-01T00:00:00Z",
            "1990-03-01T00:00:00Z",
            "1990-04-01T00:00:00Z",
            "1990-05-01T00:00:00Z",
            "1990-06-01T00:00:00Z",
            "1990-07-01T00:00:00Z",
            "1990-08-01T00:00:00Z"
        ],
        "is_scan_s": "0",
        "is_scan_t": "0",
        "is_scan_ss": [
            "0"
        ],
        "_version_": 1703902202499694592
    }
]